firebaseaio
