Metadata-Version: 2.1
Name: firebaseaio
Version: 0.1.1
Summary: A simple async python wrapper for the [Firebase API](https://firebase.google.com).
Home-page: https://github.com/09ghostrider/firebase-aio
Author: 09ghostrider
License: MIT
Project-URL: Homepage, https://github.com/09ghostrider/firebase-aio
Project-URL: Bug Tracker, https://github.com/09ghostrider/firebase-aio/issues
Keywords: firebaseaio,firebase-aio
Platform: UNKNOWN
License-File: LICENSE
